{"datasetId":2178,"busiLineId":100,"pageId":2401,"pageName":"高达活动效果分析","chartName":"多维分析","chartId":"IndicatorCard_RpDXgTQC","chartType":"Table","dims":[{"hasDimValue":true,"showName":"日(id)","dateFormat":"YYYYMMDD","dimCode":"日(id)","dimValType":2,"drillDims":[],"type":"date","filterOpt":"IN","showValueType":"originalValue","dateType":"date","uniqueName":"日(id)-j5yZ","derivedCode":"日(id)-j5yZ","sortType":"ASC","isComputed":false,"granularity":"date","isDate":1,"desc":"自然日，统计或汇总按业务发生日期进行归属，如描述订单一般采用下单日期，描述商家一般采用上线日期等。"},{"hasDimValue":true,"showName":"高达活动(name)","dimCode":"高达活动(name)","dimValType":1,"drillDims":[],"type":"string","filterOpt":"IN","showValueType":"originalValue","uniqueName":"高达活动(name)-CXwn","derivedCode":"高达活动(name)-CXwn","sortType":"DEFAULT","isComputed":false,"isDate":0,"desc":"高达搭建的活动"}],"indexs":[{"conditionalFormat":[],"showName":"高达_曝光设备数","showFormat":"no","indexCode":"曝光设备数","type":"bigint","customShowName":"高达_曝光设备数","aggrType":"count distinct","formate":{"prefix":"","dataType":"DEFAULT","dataPrecision":0,"suffix":"","dataUnit":"N","isThousands":false},"indexType":"notAggregated","uniqueName":"曝光设备数-sNFj","derivedCode":"曝光设备数-sNFj","rate":{"compareType":"NONE","offset":0,"dateField":"","offsetType":"none"},"sortType":"DESC","isComputed":false,"desc":"统计周期内，用户端某个页面/组件/元素在用户端成功展示的设备数总和。注：设备数按union_id识别进行去重处理。"},{"conditionalFormat":[],"showName":"高达_商家主页_曝光设备数","showFormat":"no","indexCode":"点菜页曝光设备数","type":"bigint","aggrType":"count distinct","formate":{"prefix":"","dataType":"DEFAULT","dataPrecision":0,"suffix":"","dataUnit":"N","isThousands":false},"indexType":"notAggregated","uniqueName":"点菜页曝光设备数-f4XH","derivedCode":"点菜页曝光设备数-f4XH","rate":{"compareType":"NONE","offset":0,"dateField":"","offsetType":"none"},"sortType":"DEFAULT","isComputed":false,"desc":"统计期内，点菜页曝光设备数按union_id去重。"},{"conditionalFormat":[],"showName":"高达_订单设备数_直接","showFormat":"number","indexCode":"高达_订单设备数_直接","type":"bigint","aggrType":"count distinct","showFormatDecimalsNum":0,"formate":{"prefix":"","dataType":"DEFAULT","dataPrecision":0,"suffix":"","dataUnit":"N","isThousands":false},"indexType":"notAggregated","uniqueName":"高达_订单设备数_直接-iWT6","derivedCode":"高达_订单设备数_直接-iWT6","rate":{"compareType":"NONE","offset":0,"dateField":"","offsetType":"none"},"sortType":"DEFAULT","isComputed":false,"desc":"在统计期内，访问高达的商家页面后，直接完成支付的设备数总和。注：①设备数按设备ID识别进行去重计数②不包括取消订单。"},{"conditionalFormat":[],"showName":"高达_交易用户数_直接","showFormat":"number","indexCode":"高达_交易用户数_直接","type":"bigint","aggrType":"count distinct","showFormatDecimalsNum":0,"formate":{"prefix":"","dataType":"DEFAULT","dataPrecision":0,"suffix":"","dataUnit":"N","isThousands":false},"indexType":"notAggregated","uniqueName":"高达_交易用户数_直接-esd5","derivedCode":"高达_交易用户数_直接-esd5","rate":{"compareType":"NONE","offset":0,"dateField":"","offsetType":"none"},"sortType":"DEFAULT","isComputed":false,"desc":"在统计期内，按照提单时间统计访问高达的商家页面后，直接完成支付订单的用户数总和。说明：①按照user_id去重；②不包括取消订单。"},{"conditionalFormat":[],"showName":"高达_订单量_直接","showFormat":"number","indexCode":"高达_订单量_直接","type":"bigint","aggrType":"sum","showFormatDecimalsNum":0,"formate":{"prefix":"","dataType":"DEFAULT","dataPrecision":0,"suffix":"","dataUnit":"N","isThousands":false},"indexType":"notAggregated","uniqueName":"高达_订单量_直接-YZZ6","derivedCode":"高达_订单量_直接-YZZ6","rate":{"compareType":"NONE","offset":0,"dateField":"","offsetType":"none"},"sortType":"DEFAULT","isComputed":false,"desc":"在统计期内，用户访问高达的商家页面后，直接完成支付的订单。说明：按照提单时间统计，不包括取消订单"},{"conditionalFormat":[],"showName":"高达_访购率_直接","showFormat":"percent","indexCode":"高达_访购率_直接","type":"double","aggrType":"default","showFormatDecimalsNum":2,"formate":{"prefix":"","dataType":"DEFAULT","dataPrecision":0,"suffix":"","dataUnit":"N","isThousands":false},"indexType":"notAggregated","uniqueName":"高达_访购率_直接-7XSB","derivedCode":"高达_访购率_直接-7XSB","rate":{"compareType":"NONE","offset":0,"dateField":"","offsetType":"none"},"sortType":"DEFAULT","isComputed":false,"desc":"[高达_订单设备数_直接]  /  [曝光设备数] "},{"conditionalFormat":[],"showName":"高达_原价单均价_直接","showFormat":"number","indexCode":"高达_原价单均价_直接","type":"double","aggrType":"default","showFormatDecimalsNum":2,"formate":{"prefix":"","dataType":"DEFAULT","dataPrecision":0,"suffix":"","dataUnit":"N","isThousands":false},"indexType":"notAggregated","uniqueName":"高达_原价单均价_直接-3YE4","derivedCode":"高达_原价单均价_直接-3YE4","rate":{"compareType":"NONE","offset":0,"dateField":"","offsetType":"none"},"sortType":"DEFAULT","isComputed":false,"desc":"高达_原价交易额_直接/高达_订单量_直接"},{"conditionalFormat":[],"showName":"高达_原价交易额_直接","showFormat":"number","indexCode":"高达_原价交易额_直接","type":"double","aggrType":"sum","showFormatDecimalsNum":2,"formate":{"prefix":"","dataType":"DEFAULT","dataPrecision":0,"suffix":"","dataUnit":"N","isThousands":false},"indexType":"notAggregated","uniqueName":"高达_原价交易额_直接-QEN7","derivedCode":"高达_原价交易额_直接-QEN7","rate":{"compareType":"NONE","offset":0,"dateField":"","offsetType":"none"},"sortType":"DEFAULT","isComputed":false,"desc":"在统计期内，用户访问高达的商家页面后，直接完成支付的订单商品原价、餐盒费以及配送费总和。说明：按照提单时间统计，不包括取消订单。"},{"conditionalFormat":[],"showName":"高达_实付交易额_直接","showFormat":"number","indexCode":"高达_实付交易额_直接","type":"double","aggrType":"sum","showFormatDecimalsNum":2,"formate":{"prefix":"","dataType":"DEFAULT","dataPrecision":0,"suffix":"","dataUnit":"N","isThousands":false},"indexType":"notAggregated","uniqueName":"高达_实付交易额_直接-3GPy","derivedCode":"高达_实付交易额_直接-3GPy","rate":{"compareType":"NONE","offset":0,"dateField":"","offsetType":"none"},"sortType":"DEFAULT","isComputed":false,"desc":"在统计期内，用户访问高达的商家页面后，直接完成支付的订单实际支付交易额合计。说明：按照提单时间统计，不包括取消订单。"},{"conditionalFormat":[],"showName":"高达_实付美团补贴率_直接","showFormat":"number","indexCode":"高达_实付美团补贴率_直接","type":"double","aggrType":"default","showFormatDecimalsNum":2,"formate":{"prefix":"","dataType":"DOUBLE","dataPrecision":2,"suffix":"%","dataUnit":"N","isThousands":false},"indexType":"notAggregated","uniqueName":"高达_实付美团补贴率_直接-sPQy","derivedCode":"高达_实付美团补贴率_直接-sPQy","rate":{"compareType":"NONE","offset":0,"dateField":"","offsetType":"none"},"sortType":"DEFAULT","isComputed":false,"desc":"高达_美团补贴金额_直接/(高达_原价交易额_直接-高达_商家补贴金额_直接)"},{"conditionalFormat":[],"showName":"高达_订单设备数_间接","showFormat":"number","indexCode":"高达_订单设备数_间接","type":"bigint","aggrType":"count distinct","showFormatDecimalsNum":0,"formate":{"prefix":"","dataType":"DEFAULT","dataPrecision":0,"suffix":"","dataUnit":"N","isThousands":false},"indexType":"notAggregated","uniqueName":"高达_订单设备数_间接-SZH8","derivedCode":"高达_订单设备数_间接-SZH8","rate":{"compareType":"NONE","offset":0,"dateField":"","offsetType":"none"},"sortType":"DEFAULT","isComputed":false,"desc":"在统计期内，按照提单时间统计访问高达的商家页面后退出，当日在同商家完成支付的订单与访问高达页面跳转至其它页面完成支付的订单（剔除直接订单）的设备数总和。注：①设备数按设备ID识别进行去重计数②按照提单时间统计，不包括取消订单。"},{"conditionalFormat":[],"showName":"高达_交易用户数_间接","showFormat":"number","indexCode":"高达_交易用户数_间接","type":"bigint","aggrType":"count distinct","showFormatDecimalsNum":0,"formate":{"prefix":"","dataType":"DEFAULT","dataPrecision":0,"suffix":"","dataUnit":"N","isThousands":false},"indexType":"notAggregated","uniqueName":"高达_交易用户数_间接-S6JM","derivedCode":"高达_交易用户数_间接-S6JM","rate":{"compareType":"NONE","offset":0,"dateField":"","offsetType":"none"},"sortType":"DEFAULT","isComputed":false,"desc":"在统计期内，访问高达的商家页面后退出，当日在同商家完成支付的订单与访问高达页面跳转至其它页面完成支付的订单（剔除直接订单）的用户数总和。说明：①按照user_id去重；②按照提单时间统计，不包括取消订单。"},{"conditionalFormat":[],"showName":"高达_订单量_间接","showFormat":"number","indexCode":"高达_订单量_间接","type":"bigint","aggrType":"sum","showFormatDecimalsNum":0,"formate":{"prefix":"","dataType":"DEFAULT","dataPrecision":0,"suffix":"","dataUnit":"N","isThousands":false},"indexType":"notAggregated","uniqueName":"高达_订单量_间接-apyT","derivedCode":"高达_订单量_间接-apyT","rate":{"compareType":"NONE","offset":0,"dateField":"","offsetType":"none"},"sortType":"DEFAULT","isComputed":false,"desc":"在统计期内，访问高达的商家页面后退出，当日在同商家完成支付的订单与访问高达页面跳转至其它页面完成支付的订单合计（剔除直接订单）。说明：按照提单时间统计，不包括取消订单"},{"conditionalFormat":[],"showName":"高达_原价单均价_间接","showFormat":"number","indexCode":"高达_原价单均价_间接","type":"double","aggrType":"default","showFormatDecimalsNum":2,"formate":{"prefix":"","dataType":"DEFAULT","dataPrecision":0,"suffix":"","dataUnit":"N","isThousands":false},"indexType":"notAggregated","uniqueName":"高达_原价单均价_间接-tk5C","derivedCode":"高达_原价单均价_间接-tk5C","rate":{"compareType":"NONE","offset":0,"dateField":"","offsetType":"none"},"sortType":"DEFAULT","isComputed":false,"desc":"高达_原价交易额_间接/高达_订单量_间接"},{"conditionalFormat":[],"showName":"高达_原价交易额_间接","showFormat":"number","indexCode":"高达_原价交易额_间接","type":"double","aggrType":"sum","showFormatDecimalsNum":2,"formate":{"prefix":"","dataType":"DEFAULT","dataPrecision":0,"suffix":"","dataUnit":"N","isThousands":false},"indexType":"notAggregated","uniqueName":"高达_原价交易额_间接-YrrJ","derivedCode":"高达_原价交易额_间接-YrrJ","rate":{"compareType":"NONE","offset":0,"dateField":"","offsetType":"none"},"sortType":"DEFAULT","isComputed":false,"desc":"在统计期内，访问高达的商家页面后退出，当日在同商家完成支付的订单与访问高达页面跳转至其它页面完成支付的订单（剔除直接订单）商品原价、餐盒费以及配送费总和。说明：按照提单时间统计，不包括取消订单。"},{"conditionalFormat":[],"showName":"高达_实付交易额_间接","showFormat":"number","indexCode":"高达_实付交易额_间接","type":"double","aggrType":"sum","showFormatDecimalsNum":2,"formate":{"prefix":"","dataType":"DEFAULT","dataPrecision":0,"suffix":"","dataUnit":"N","isThousands":false},"indexType":"notAggregated","uniqueName":"高达_实付交易额_间接-4fwn","derivedCode":"高达_实付交易额_间接-4fwn","rate":{"compareType":"NONE","offset":0,"dateField":"","offsetType":"none"},"sortType":"DEFAULT","isComputed":false,"desc":"在统计期内，访问高达的商家页面后退出，当日在同商家完成支付的订单与访问高达页面跳转至其它页面完成支付的订单（剔除直接订单）实际支付交易额合计。说明：按照提单时间统计，不包括取消订单。"},{"conditionalFormat":[],"showName":"高达_访购率_间接","showFormat":"percent","indexCode":"高达_访购率_间接","type":"double","aggrType":"default","showFormatDecimalsNum":2,"formate":{"prefix":"","dataType":"DEFAULT","dataPrecision":0,"suffix":"","dataUnit":"N","isThousands":false},"indexType":"notAggregated","uniqueName":"高达_访购率_间接-ZEdC","derivedCode":"高达_访购率_间接-ZEdC","rate":{"compareType":"NONE","offset":0,"dateField":"","offsetType":"none"},"sortType":"DEFAULT","isComputed":false,"desc":"[高达_订单设备数_间接]  /  [曝光设备数] "},{"conditionalFormat":[],"showName":"高达_实付美团补贴率_间接","showFormat":"number","indexCode":"高达_实付美团补贴率_间接","type":"double","aggrType":"default","showFormatDecimalsNum":2,"formate":{"prefix":"","dataType":"DOUBLE","dataPrecision":2,"suffix":"%","dataUnit":"N","isThousands":false},"indexType":"notAggregated","uniqueName":"高达_实付美团补贴率_间接-pbEW","derivedCode":"高达_实付美团补贴率_间接-pbEW","rate":{"compareType":"NONE","offset":0,"dateField":"","offsetType":"none"},"sortType":"DEFAULT","isComputed":false,"desc":"高达_美团补贴金额_间接/(高达_原价交易额_间接-高达_商家补贴金额_间接)"}],"queryFeatures":{"rates":[],"meta":{"customDimAndIndex":[]}},"filters":[{"filterType":"DATE","optType":"BETWEEN","values":[["20260215"],["20260315"]],"dParamFlag":false,"keyCodes":["日(id)"],"keyCodesType":["dim"]},{"filterType":"REGULAR","optType":"IN","values":[["102","616314"]],"dParamFlag":false,"keyCodes":["高达团队(id)","高达活动(id)"],"keyCodesType":["dim","dim"]}],"pageNum":1,"pageSize":10,"useCache":1,"queryDomain":"preview"}